fittingtools/__init__.py
fittingtools/least_squares.py
fittingtools-0.1.5.dist-info/METADATA
fittingtools-0.1.5.dist-info/WHEEL
fittingtools-0.1.5.dist-info/licenses/LICENSE
fittingtools-0.1.5.dist-info/RECORD
