Metadata-Version: 2.4
Name: fittingtools
Version: 0.1.5
Summary: Tools to get prediction intervals when using scipy's least_squares minimizer
Project-URL: Homepage, https://github.com/erickmartinez/fittingtools
Project-URL: Issues, https://github.com/erickmartinez/fittingtools/issues
Author-email: Erick Martinez Loran <erickrmartinez@gmail.com>
License-Expression: MIT
License-File: LICENSE
Classifier: Operating System :: OS Independent
Classifier: Programming Language :: Python :: 3
Requires-Python: >=3.8
